setup.py
scopetest/__init__.py
scopetest.egg-info/PKG-INFO
scopetest.egg-info/SOURCES.txt
scopetest.egg-info/dependency_links.txt
scopetest.egg-info/not-zip-safe
scopetest.egg-info/top_level.txt